{
  "type_description_msg": {
    "type_description": {
      "type_name": "franka_msgs/srv/SetFullCollisionBehavior_Response",
      "fields": [
        {
          "name": "success",
          "type": {
            "type_id": 15,
            "capacity": 0,
            "string_capacity": 0,
            "nested_type_name": ""
          },
          "default_value": ""
        },
        {
          "name": "error",
          "type": {
            "type_id": 17,
            "capacity": 0,
            "string_capacity": 0,
            "nested_type_name": ""
          },
          "default_value": ""
        }
      ]
    },
    "referenced_type_descriptions": []
  },
  "type_hashes": [
    {
      "type_name": "franka_msgs/srv/SetFullCollisionBehavior_Response",
      "hash_string": "RIHS01_44c69b6330cd839a5d91b276c3679a272650d591df9664315ef7f50e9f116caf"
    }
  ]
}