{
  "type_description_msg": {
    "type_description": {
      "type_name": "franka_msgs/action/Grasp_FeedbackMessage",
      "fields": [
        {
          "name": "goal_id",
          "type": {
            "type_id": 1,
            "capacity": 0,
            "string_capacity": 0,
            "nested_type_name": "unique_identifier_msgs/msg/UUID"
          },
          "default_value": ""
        },
        {
          "name": "feedback",
          "type": {
            "type_id": 1,
            "capacity": 0,
            "string_capacity": 0,
            "nested_type_name": "franka_msgs/action/Grasp_Feedback"
          },
          "default_value": ""
        }
      ]
    },
    "referenced_type_descriptions": [
      {
        "type_name": "franka_msgs/action/Grasp_Feedback",
        "fields": [
          {
            "name": "current_width",
            "type": {
              "type_id": 11,
              "capacity": 0,
              "string_capacity": 0,
              "nested_type_name": ""
            },
            "default_value": ""
          }
        ]
      },
      {
        "type_name": "unique_identifier_msgs/msg/UUID",
        "fields": [
          {
            "name": "uuid",
            "type": {
              "type_id": 51,
              "capacity": 16,
              "string_capacity": 0,
              "nested_type_name": ""
            },
            "default_value": ""
          }
        ]
      }
    ]
  },
  "type_hashes": [
    {
      "type_name": "franka_msgs/action/Grasp_FeedbackMessage",
      "hash_string": "RIHS01_7b7a00a66aed431831ac3b2fda6e165401a3f9789c4f9dbdd2092ba75961b603"
    },
    {
      "type_name": "franka_msgs/action/Grasp_Feedback",
      "hash_string": "RIHS01_98e46899b441d2f450da39a69d2518312fefaf7e4ba7d24e4128ba5c2649f4a1"
    },
    {
      "type_name": "unique_identifier_msgs/msg/UUID",
      "hash_string": "RIHS01_1b8e8aca958cbea28fe6ef60bf6c19b683c97a9ef60bb34752067d0f2f7ab437"
    }
  ]
}